Metadata-Version: 2.4
Name: llama-index-packs-stock-market-data-query-engine
Version: 0.5.1
Summary: llama-index packs stock_market_data_query_engine integration
Author-email: Your Name <you@example.com>
Maintainer: anoopshrma
License-Expression: MIT
License-File: LICENSE
Keywords: data,engine,finance,market,query,stock,yahoo,yahoo finance
Requires-Python: <4.0,>=3.9
Requires-Dist: llama-index-core<0.15,>=0.13.0
Requires-Dist: llama-index-llms-openai<0.6,>=0.5.0
Requires-Dist: yfinance<0.3,>=0.2.36
